pytest_hpfeeds/__init__.py
pytest_hpfeeds/plugin.py
pytest_hpfeeds-0.2.8.dist-info/LICENSE
pytest_hpfeeds-0.2.8.dist-info/METADATA
pytest_hpfeeds-0.2.8.dist-info/WHEEL
pytest_hpfeeds-0.2.8.dist-info/entry_points.txt
pytest_hpfeeds-0.2.8.dist-info/RECORD
