Metadata-Version: 2.1
Name: pytest-hpfeeds
Version: 0.2.8
Summary: Helpers for testing hpfeeds in your python project
Home-page: https://github.com/hpfeeds/pytest-hpfeeds
License: Apache-2.0
Author: John Carr
Author-email: john.carr@unrouted.co.uk
Requires-Python: >=3.8,<4.0
Classifier: Development Status :: 4 - Beta
Classifier: Intended Audience :: Developers
Classifier: License :: OSI Approved :: Apache Software License
Classifier: Programming Language :: Python :: 3
Classifier: Programming Language :: Python :: 3.8
Classifier: Programming Language :: Python :: 3.9
Classifier: Programming Language :: Python :: 3.10
Classifier: Programming Language :: Python :: 3.11
Classifier: Programming Language :: Python :: 3.8
Classifier: Programming Language :: Python :: 3.9
Classifier: Topic :: Software Development :: Testing
Requires-Dist: hpfeeds (>=3.0.0,<4.0.0)
Requires-Dist: pytest (>=6.2.4,<7.0.0)
Requires-Dist: pytest-aiohttp (>=0.3.0,<0.4.0)
Requires-Dist: pytest-docker-tools (>=3.1.0,<4.0.0)
